rocket_fft-0.3.1.dist-info/RECORD
rocket_fft-0.3.1.dist-info/WHEEL
rocket_fft-0.3.1.dist-info/entry_points.txt
rocket_fft-0.3.1.dist-info/top_level.txt
rocket_fft-0.3.1.dist-info/METADATA
rocket_fft-0.3.1.dist-info/licenses/LICENSE
rocket_fft/_pocketfft_hdronly.h
rocket_fft/__init__.pyi
rocket_fft/_version.py
rocket_fft/imputils.py
rocket_fft/__init__.py
rocket_fft/typutils.py
rocket_fft/_special_helpers.cpython-313-darwin.so
rocket_fft/overloads.py
rocket_fft/_pocketfft_numba.cpp
rocket_fft/_pocketfft_numba.cpython-313-darwin.so
rocket_fft/py.typed
rocket_fft/pocketfft.py
rocket_fft/_special_helpers.cpp
rocket_fft/special.py
rocket_fft/extutils.py
