Metadata-Version: 2.4
Name: rocket-fft
Version: 0.3.1
Summary: Rocket-FFT extends Numba by scipy.fft and numpy.fft
Author-email: Styfen Schär <styfen.schaer.blog@gmail.com>
License: BSD-3-Clause
Project-URL: Homepage, https://github.com/styfenschaer/rocket-fft
Project-URL: Repository, https://github.com/styfenschaer/rocket-fft
Keywords: FFT,Fourier,Numba,SciPy,NumPy
Classifier: Development Status :: 4 - Beta
Classifier: License :: OSI Approved :: BSD License
Classifier: Operating System :: OS Independent
Classifier: Topic :: Scientific/Engineering
Classifier: Topic :: Software Development
Classifier: Intended Audience :: Science/Research
Classifier: Intended Audience :: Developers
Classifier: Intended Audience :: Education
Classifier: Programming Language :: Python :: 3
Classifier: Programming Language :: Python :: 3.9
Classifier: Programming Language :: Python :: 3.10
Classifier: Programming Language :: Python :: 3.11
Classifier: Programming Language :: Python :: 3.12
Classifier: Programming Language :: Python :: 3.13
Classifier: Programming Language :: Python :: 3.14
Requires-Python: >=3.9
License-File: LICENSE
Requires-Dist: numba>=0.60.0
Provides-Extra: dev
Requires-Dist: scipy>=1.13.1; extra == "dev"
Requires-Dist: pytest>=8.4.2; extra == "dev"
Dynamic: license-file
